yeelight/__init__.py
yeelight/aio.py
yeelight/decorator.py
yeelight/enums.py
yeelight/flow.py
yeelight/flows.py
yeelight/main.py
yeelight/metadata.py
yeelight/ssdp_discover.py
yeelight/tests.py
yeelight/transitions.py
yeelight/utils.py
yeelight-0.7.14.dist-info/LICENSE
yeelight-0.7.14.dist-info/WHEEL
yeelight-0.7.14.dist-info/METADATA
yeelight-0.7.14.dist-info/RECORD
