Metadata-Version: 2.1
Name: yeelight
Version: 0.7.14
Summary: A Python library for controlling YeeLight RGB bulbs.
Author-email: Stavros Korokithakis <hi@stavros.io>
Requires-Python: >=3.4
Classifier: License :: OSI Approved :: BSD License
Classifier: Programming Language :: Python
Classifier: Programming Language :: Python :: 3.4
Classifier: Programming Language :: Python :: 3.5
Classifier: Programming Language :: Python :: 3.6
Classifier: Programming Language :: Python :: 3.7
Classifier: Programming Language :: Python :: 3.8
Classifier: Topic :: Software Development :: Libraries :: Python Modules
Requires-Dist: future
Requires-Dist: ifaddr
Requires-Dist: importlib_metadata; python_version<'3.8'
Requires-Dist: async-timeout; python_version<'3.11'
Requires-Dist: flake8 ; extra == "dev"
Requires-Dist: flake8-docstrings ; extra == "dev"
Requires-Dist: flake8-import-order ; extra == "dev"
Requires-Dist: flake8-tidy-imports ; extra == "dev"
Requires-Dist: pep8-naming ; extra == "dev"
Requires-Dist: Sphinx ; extra == "dev"
Requires-Dist: sphinx-rtd-theme ; extra == "dev"
Project-URL: Homepage, https://gitlab.com/stavros/python-yeelight
Provides-Extra: dev
